betfair_api_client/__init__.py
betfair_api_client/betfair_client.py
betfair_api_client/datamodel/__init__.py
betfair_api_client/datamodel/bet_types.py
betfair_api_client/datamodel/competition.py
betfair_api_client/datamodel/event.py
betfair_api_client/datamodel/exceptions.py
betfair_api_client/datamodel/market.py
betfair_api_client/datamodel/market_types.py
betfair_api_client/datamodel/runner.py
betfair_api_client/datamodel/runner_price.py
betfair_api_client/tests/__init__.py
betfair_api_client/tests/test_betfair_api_client.py
betfair_api_client/tests/test_event.py
betfair_api_client/tests/test_market.py
betfair_api_client/tests/test_runner.py
betfair_api_client-0.4.2.dist-info/LICENSE
betfair_api_client-0.4.2.dist-info/METADATA
betfair_api_client-0.4.2.dist-info/WHEEL
betfair_api_client-0.4.2.dist-info/top_level.txt
betfair_api_client-0.4.2.dist-info/RECORD
