Metadata-Version: 2.1
Name: betfair-api-client
Version: 0.4.2
Summary: Client for connecting to the Betfair Odds API and fetch betting market info
Home-page: https://github.com/miksyr/betfair_api_client
Author: Michael Doran
Author-email: mikrdoran@gmail.com
License: UNKNOWN
Download-URL: https://github.com/miksyr/betfair_api_client/archive/v_04.tar.gz
Keywords: betfair,betfair odds api,sports betting
Platform: UNKNOWN
Classifier: Programming Language :: Python :: 3
Classifier: License :: OSI Approved :: GNU General Public License v3 (GPLv3)
Classifier: Operating System :: OS Independent
Requires-Dist: requests (>=2.24.0)
